pynter/__init__.py
pynter/config_default.yml
pynter/cli/analysis.py
pynter/cli/automations.py
pynter/cli/config.py
pynter/cli/hpc.py
pynter/cli/main.py
pynter/cli/materials_project.py
pynter/cli/plotter.py
pynter/cli/slurm.py
pynter/cli/utils.py
pynter/hpc/__init__.py
pynter/hpc/sbatch_arguments.txt
pynter/hpc/sbatch_arguments_help.txt
pynter/hpc/slurm.py
pynter/hpc/ssh.py
pynter/jobs/__init__.py
pynter/jobs/core.py
pynter/jobs/datasets.py
pynter/jobs/manager.py
pynter/jobs/lammps/lammps_jobs.py
pynter/jobs/vasp/vasp_automations.py
pynter/jobs/vasp/vasp_jobs.py
pynter/lammps/__init__.py
pynter/lammps/inputs.py
pynter/lammps/lammps_default.yml
pynter/lammps/schemes/core.py
pynter/lammps/schemes/machine_learning.py
pynter/testing/__init__.py
pynter/testing/core.py
pynter/testing/hpc.py
pynter/testing/jobs.py
pynter/testing/structure.py
pynter/testing/vasp.py
pynter/tools/__init__.py
pynter/tools/format.py
pynter/tools/materials_project.py
pynter/tools/plotter.py
pynter/tools/structure.py
pynter/tools/utils.py
pynter/vasp/__init__.py
pynter/vasp/analysis.py
pynter/vasp/plotter.py
pynter/vasp/utils.py
pynter/vasp/vasp_default.yml
pynter/vasp/pmg/pmg_electronic_structure_dos.py
pynter/vasp/pmg/pmg_electronic_structure_plotter.py
pynter/vasp/schemes/__init__.py
pynter/vasp/schemes/core.py
pynter/vasp/schemes/defects.py
pynter/vasp/schemes/electronic_structure.py
pynter/vasp/schemes/neb.py
pynter/vasp/schemes/relaxation.py
pynter/vasp/schemes/variations.py
pynter2-2.0.0.dist-info/METADATA
pynter2-2.0.0.dist-info/WHEEL
pynter2-2.0.0.dist-info/entry_points.txt
pynter2-2.0.0.dist-info/top_level.txt
pynter2-2.0.0.dist-info/RECORD
