Metadata-Version: 2.4
Name: pynter2
Version: 2.0.0
Summary: Tools for atomistic calculations, provides features for point-defect calculations
Author: Lorenzo Villa
Requires-Dist: ase
Requires-Dist: paramiko
Requires-Dist: pymatgen>=2023.3.23
Requires-Dist: PyYAML
Requires-Dist: schedule
Dynamic: author
Dynamic: description
Dynamic: description-content-type
Dynamic: requires-dist
Dynamic: summary
